{
	"bottomAmount": 88000,
	"bottomRate": 3.063,
	"condition": [
		{
			"boundary": 89000,
			"fuyou": {
				"rate": null,
				"amount": [130, 0, 0, 0, 0, 0, 0, 0]	
			},
			"otsu": {
				"rate": null,
				"amount": 3200
			}
		},
		{
			"boundary": 90000,
			"fuyou": {
				"rate": null,
				"amount": [180, 0, 0, 0, 0, 0, 0, 0]	
			},
			"otsu": {
				"rate": null,
				"amount": 3200
			}
		},
		{
			"boundary": 91000,
			"fuyou": {
				"rate": null,
				"amount": [230, 0, 0, 0, 0, 0, 0, 0]	
			},
			"otsu": {
				"rate": null,
				"amount": 3200
			}
		},
		{
			"boundary": 92000,
			"fuyou": {
				"rate": null,
				"amount": [290, 0, 0, 0, 0, 0, 0, 0]	
			},
			"otsu": {
				"rate": null,
				"amount": 3200
			}
		},
		{
			"boundary": 93000,
			"fuyou": {
				"rate": null,
				"amount": [340, 0, 0, 0, 0, 0, 0, 0]	
			},
			"otsu": {
				"rate": null,
				"amount": 3300
			}
		},
		{
			"boundary": 94000,
			"fuyou": {
				"rate": null,
				"amount": [390, 0, 0, 0, 0, 0, 0, 0]	
			},
			"otsu": {
				"rate": null,
				"amount": 3300
			}
		},
		{
			"boundary": 95000,
			"fuyou": {
				"rate": null,
				"amount": [440, 0, 0, 0, 0, 0, 0, 0]	
			},
			"otsu": {
				"rate": null,
				"amount": 3300
			}
		},
		{
			"boundary": 96000,
			"fuyou": {
				"rate": null,
				"amount": [490, 0, 0, 0, 0, 0, 0, 0]	
			},
			"otsu": {
				"rate": null,
				"amount": 3400
			}
		},
		{
			"boundary": 97000,
			"fuyou": {
				"rate": null,
				"amount": [540, 0, 0, 0, 0, 0, 0, 0]	
			},
			"otsu": {
				"rate": null,
				"amount": 3400
			}
		},
		{
			"boundary": 98000,
			"fuyou": {
				"rate": null,
				"amount": [590, 0, 0, 0, 0, 0, 0, 0]	
			},
			"otsu": {
				"rate": null,
				"amount": 3500
			}
		},
		{
			"boundary": 99000,
			"fuyou": {
				"rate": null,
				"amount": [640, 0, 0, 0, 0, 0, 0, 0]	
			},
			"otsu": {
				"rate": null,
				"amount": 3500
			}
		},
		{
			"boundary": 101000,
			"fuyou": {
				"rate": null,
				"amount": [720, 0, 0, 0, 0, 0, 0, 0]	
			},
			"otsu": {
				"rate": null,
				"amount": 3600
			}
		},
		{
			"boundary": 103000,
			"fuyou": {
				"rate": null,
				"amount": [830, 0, 0, 0, 0, 0, 0, 0]	
			},
			"otsu": {
				"rate": null,
				"amount": 3600
			}
		},
		{
			"boundary": 105000,
			"fuyou": {
				"rate": null,
				"amount": [930, 0, 0, 0, 0, 0, 0, 0]	
			},
			"otsu": {
				"rate": null,
				"amount": 3700
			}
		},
		{
			"boundary": 107000,
			"fuyou": {
				"rate": null,
				"amount": [1030, 0, 0, 0, 0, 0, 0, 0]	
			},
			"otsu": {
				"rate": null,
				"amount": 3800
			}
		},
		{
			"boundary": 109000,
			"fuyou": {
				"rate": null,
				"amount": [1130, 0, 0, 0, 0, 0, 0, 0]	
			},
			"otsu": {
				"rate": null,
				"amount": 3800
			}
		},
		{
			"boundary": 111000,
			"fuyou": {
				"rate": null,
				"amount": [1240, 0, 0, 0, 0, 0, 0, 0]	
			},
			"otsu": {
				"rate": null,
				"amount": 3900
			}
		},
		{
			"boundary": 113000,
			"fuyou": {
				"rate": null,
				"amount": [1340, 0, 0, 0, 0, 0, 0, 0]	
			},
			"otsu": {
				"rate": null,
				"amount": 4000
			}
		},
		{
			"boundary": 115000,
			"fuyou": {
				"rate": null,
				"amount": [1440, 0, 0, 0, 0, 0, 0, 0]	
			},
			"otsu": {
				"rate": null,
				"amount": 4100
			}
		},
		{
			"boundary": 117000,
			"fuyou": {
				"rate": null,
				"amount": [1540, 0, 0, 0, 0, 0, 0, 0]	
			},
			"otsu": {
				"rate": null,
				"amount": 4100
			}
		},
		{
			"boundary": 119000,
			"fuyou": {
				"rate": null,
				"amount": [1640, 0, 0, 0, 0, 0, 0, 0]	
			},
			"otsu": {
				"rate": null,
				"amount": 4200
			}
		},
		{
			"boundary": 121000,
			"fuyou": {
				"rate": null,
				"amount": [1750, 120, 0, 0, 0, 0, 0, 0]	
			},
			"otsu": {
				"rate": null,
				"amount": 4300
			}
		},
		{
			"boundary": 123000,
			"fuyou": {
				"rate": null,
				"amount": [1850, 220, 0, 0, 0, 0, 0, 0]	
			},
			"otsu": {
				"rate": null,
				"amount": 4500
			}
		},
		{
			"boundary": 125000,
			"fuyou": {
				"rate": null,
				"amount": [1950, 330, 0, 0, 0, 0, 0, 0]	
			},
			"otsu": {
				"rate": null,
				"amount": 4800
			}
		},
		{
			"boundary": 127000,
			"fuyou": {
				"rate": null,
				"amount": [2050, 430, 0, 0, 0, 0, 0, 0]	
			},
			"otsu": {
				"rate": null,
				"amount": 5100
			}
		},
		{
			"boundary": 129000,
			"fuyou": {
				"rate": null,
				"amount": [2150, 530, 0, 0, 0, 0, 0, 0]	
			},
			"otsu": {
				"rate": null,
				"amount": 5400
			}
		},
		{
			"boundary": 131000,
			"fuyou": {
				"rate": null,
				"amount": [2260, 630, 0, 0, 0, 0, 0, 0]	
			},
			"otsu": {
				"rate": null,
				"amount": 5700
			}
		},
		{
			"boundary": 133000,
			"fuyou": {
				"rate": null,
				"amount": [2360, 740, 0, 0, 0, 0, 0, 0]	
			},
			"otsu": {
				"rate": null,
				"amount": 6000
			}
		},
		{
			"boundary": 135000,
			"fuyou": {
				"rate": null,
				"amount": [2460, 840, 0, 0, 0, 0, 0, 0]	
			},
			"otsu": {
				"rate": null,
				"amount": 6300
			}
		},
		{
			"boundary": 137000,
			"fuyou": {
				"rate": null,
				"amount": [2550, 930, 0, 0, 0, 0, 0, 0]	
			},
			"otsu": {
				"rate": null,
				"amount": 6600
			}
		},
		{
			"boundary": 139000,
			"fuyou": {
				"rate": null,
				"amount": [2610, 990, 0, 0, 0, 0, 0, 0]	
			},
			"otsu": {
				"rate": null,
				"amount": 6800
			}
		},
		{
			"boundary": 141000,
			"fuyou": {
				"rate": null,
				"amount": [2680, 1050, 0, 0, 0, 0, 0, 0]	
			},
			"otsu": {
				"rate": null,
				"amount": 7100
			}
		},
		{
			"boundary": 143000,
			"fuyou": {
				"rate": null,
				"amount": [2740, 1110, 0, 0, 0, 0, 0, 0]	
			},
			"otsu": {
				"rate": null,
				"amount": 7500
			}
		},
		{
			"boundary": 145000,
			"fuyou": {
				"rate": null,
				"amount": [2800, 1170, 0, 0, 0, 0, 0, 0]	
			},
			"otsu": {
				"rate": null,
				"amount": 7800
			}
		},
		{
			"boundary": 147000,
			"fuyou": {
				"rate": null,
				"amount": [2860, 1240, 0, 0, 0, 0, 0, 0]	
			},
			"otsu": {
				"rate": null,
				"amount": 8100
			}
		},
		{
			"boundary": 149000,
			"fuyou": {
				"rate": null,
				"amount": [2920, 1300, 0, 0, 0, 0, 0, 0]	
			},
			"otsu": {
				"rate": null,
				"amount": 8400
			}
		},
		{
			"boundary": 151000,
			"fuyou": {
				"rate": null,
				"amount": [2980, 1360, 0, 0, 0, 0, 0, 0]	
			},
			"otsu": {
				"rate": null,
				"amount": 8700
			}
		},
		{
			"boundary": 153000,
			"fuyou": {
				"rate": null,
				"amount": [3050, 1430, 0, 0, 0, 0, 0, 0]	
			},
			"otsu": {
				"rate": null,
				"amount": 9000
			}
		},
		{
			"boundary": 155000,
			"fuyou": {
				"rate": null,
				"amount": [3120, 1500, 0, 0, 0, 0, 0, 0]	
			},
			"otsu": {
				"rate": null,
				"amount": 9300
			}
		},
		{
			"boundary": 157000,
			"fuyou": {
				"rate": null,
				"amount": [3200, 1570, 0, 0, 0, 0, 0, 0]	
			},
			"otsu": {
				"rate": null,
				"amount": 9600
			}
		},
		{
			"boundary": 159000,
			"fuyou": {
				"rate": null,
				"amount": [3270, 1640, 0, 0, 0, 0, 0, 0]	
			},
			"otsu": {
				"rate": null,
				"amount": 9900
			}
		},
		{
			"boundary": 161000,
			"fuyou": {
				"rate": null,
				"amount": [3340, 1720, 100, 0, 0, 0, 0, 0]	
			},
			"otsu": {
				"rate": null,
				"amount": 10200
			}
		},
		{
			"boundary": 163000,
			"fuyou": {
				"rate": null,
				"amount": [3410, 1790, 170, 0, 0, 0, 0, 0]	
			},
			"otsu": {
				"rate": null,
				"amount": 10500
			}
		},
		{
			"boundary": 165000,
			"fuyou": {
				"rate": null,
				"amount": [3480, 1860, 250, 0, 0, 0, 0, 0]	
			},
			"otsu": {
				"rate": null,
				"amount": 10800
			}
		},
		{
			"boundary": 167000,
			"fuyou": {
				"rate": null,
				"amount": [3550, 1930, 320, 0, 0, 0, 0, 0]	
			},
			"otsu": {
				"rate": null,
				"amount": 11100
			}
		},
		{
			"boundary": 169000,
			"fuyou": {
				"rate": null,
				"amount": [3620, 2000, 390, 0, 0, 0, 0, 0]	
			},
			"otsu": {
				"rate": null,
				"amount": 11400
			}
		},
		{
			"boundary": 171000,
			"fuyou": {
				"rate": null,
				"amount": [3700, 2070, 460, 0, 0, 0, 0, 0]	
			},
			"otsu": {
				"rate": null,
				"amount": 11700
			}
		},
		{
			"boundary": 173000,
			"fuyou": {
				"rate": null,
				"amount": [3770, 2140, 530, 0, 0, 0, 0, 0]	
			},
			"otsu": {
				"rate": null,
				"amount": 12000
			}
		},
		{
			"boundary": 175000,
			"fuyou": {
				"rate": null,
				"amount": [3840, 2220, 600, 0, 0, 0, 0, 0]	
			},
			"otsu": {
				"rate": null,
				"amount": 12400
			}
		},
		{
			"boundary": 177000,
			"fuyou": {
				"rate": null,
				"amount": [3910, 2290, 670, 0, 0, 0, 0, 0]	
			},
			"otsu": {
				"rate": null,
				"amount": 12700
			}
		},
		{
			"boundary": 179000,
			"fuyou": {
				"rate": null,
				"amount": [3980, 2360, 750, 0, 0, 0, 0, 0]	
			},
			"otsu": {
				"rate": null,
				"amount": 13200
			}
		},
		{
			"boundary": 181000,
			"fuyou": {
				"rate": null,
				"amount": [4050, 2430, 820, 0, 0, 0, 0, 0]	
			},
			"otsu": {
				"rate": null,
				"amount": 13900
			}
		},
		{
			"boundary": 183000,
			"fuyou": {
				"rate": null,
				"amount": [4120, 2500, 890, 0, 0, 0, 0, 0]	
			},
			"otsu": {
				"rate": null,
				"amount": 14600
			}
		},
		{
			"boundary": 185000,
			"fuyou": {
				"rate": null,
				"amount": [4200, 2570, 960, 0, 0, 0, 0, 0]	
			},
			"otsu": {
				"rate": null,
				"amount": 15300
			}
		},
		{
			"boundary": 187000,
			"fuyou": {
				"rate": null,
				"amount": [4270, 2640, 1030, 0, 0, 0, 0, 0]	
			},
			"otsu": {
				"rate": null,
				"amount": 16000
			}
		},
		{
			"boundary": 189000,
			"fuyou": {
				"rate": null,
				"amount": [4340, 2720, 1100, 0, 0, 0, 0, 0]	
			},
			"otsu": {
				"rate": null,
				"amount": 16700
			}
		},
		{
			"boundary": 191000,
			"fuyou": {
				"rate": null,
				"amount": [4410, 2790, 1170, 0, 0, 0, 0, 0]	
			},
			"otsu": {
				"rate": null,
				"amount": 17500
			}
		},
		{
			"boundary": 193000,
			"fuyou": {
				"rate": null,
				"amount": [4480, 2860, 1250, 0, 0, 0, 0, 0]	
			},
			"otsu": {
				"rate": null,
				"amount": 18100
			}
		},
		{
			"boundary": 195000,
			"fuyou": {
				"rate": null,
				"amount": [4550, 2930, 1320, 0, 0, 0, 0, 0]	
			},
			"otsu": {
				"rate": null,
				"amount": 18800
			}
		},
		{
			"boundary": 197000,
			"fuyou": {
				"rate": null,
				"amount": [4630, 3000, 1390, 0, 0, 0, 0, 0]	
			},
			"otsu": {
				"rate": null,
				"amount": 19500
			}
		},
		{
			"boundary": 199000,
			"fuyou": {
				"rate": null,
				"amount": [4700, 3070, 1460, 0, 0, 0, 0, 0]	
			},
			"otsu": {
				"rate": null,
				"amount": 20200
			}
		},
		{
			"boundary": 201000,
			"fuyou": {
				"rate": null,
				"amount": [4770, 3140, 1530, 0, 0, 0, 0, 0]	
			},
			"otsu": {
				"rate": null,
				"amount": 20900
			}
		},
		{
			"boundary": 203000,
			"fuyou": {
				"rate": null,
				"amount": [4840, 3220, 1600, 0, 0, 0, 0, 0]	
			},
			"otsu": {
				"rate": null,
				"amount": 21500
			}
		},
		{
			"boundary": 205000,
			"fuyou": {
				"rate": null,
				"amount": [4910, 3290, 1670, 0, 0, 0, 0, 0]	
			},
			"otsu": {
				"rate": null,
				"amount": 22200
			}
		},
		{
			"boundary": 207000,
			"fuyou": {
				"rate": null,
				"amount": [4980, 3360, 1750, 130, 0, 0, 0, 0]	
			},
			"otsu": {
				"rate": null,
				"amount": 22700
			}
		},
		{
			"boundary": 209000,
			"fuyou": {
				"rate": null,
				"amount": [5050, 3430, 1820, 200, 0, 0, 0, 0]	
			},
			"otsu": {
				"rate": null,
				"amount": 23300
			}
		},
		{
			"boundary": 211000,
			"fuyou": {
				"rate": null,
				"amount": [5130, 3500, 1890, 280, 0, 0, 0, 0]	
			},
			"otsu": {
				"rate": null,
				"amount": 23900
			}
		},
		{
			"boundary": 213000,
			"fuyou": {
				"rate": null,
				"amount": [5200, 3570, 1960, 350, 0, 0, 0, 0]	
			},
			"otsu": {
				"rate": null,
				"amount": 24400
			}
		},
		{
			"boundary": 215000,
			"fuyou": {
				"rate": null,
				"amount": [5270, 3640, 2030, 420, 0, 0, 0, 0]	
			},
			"otsu": {
				"rate": null,
				"amount": 25000
			}
		},
		{
			"boundary": 217000,
			"fuyou": {
				"rate": null,
				"amount": [5340, 3720, 2100, 490, 0, 0, 0, 0]	
			},
			"otsu": {
				"rate": null,
				"amount": 25500
			}
		},
		{
			"boundary": 219000,
			"fuyou": {
				"rate": null,
				"amount": [5410, 3790, 2170, 560, 0, 0, 0, 0]	
			},
			"otsu": {
				"rate": null,
				"amount": 26100
			}
		},
		{
			"boundary": 221000,
			"fuyou": {
				"rate": null,
				"amount": [5480, 3860, 2250, 630, 0, 0, 0, 0]	
			},
			"otsu": {
				"rate": null,
				"amount": 26800
			}
		},
		{
			"boundary": 224000,
			"fuyou": {
				"rate": null,
				"amount": [5560, 3950, 2340, 710, 0, 0, 0, 0]	
			},
			"otsu": {
				"rate": null,
				"amount": 27400
			}
		},
		{
			"boundary": 227000,
			"fuyou": {
				"rate": null,
				"amount": [5680, 4060, 2440, 830, 0, 0, 0, 0]	
			},
			"otsu": {
				"rate": null,
				"amount": 28400
			}
		},
		{
			"boundary": 230000,
			"fuyou": {
				"rate": null,
				"amount": [5780, 4170, 2550, 930, 0, 0, 0, 0]	
			},
			"otsu": {
				"rate": null,
				"amount": 29300
			}
		},
		{
			"boundary": 233000,
			"fuyou": {
				"rate": null,
				"amount": [5890, 4280, 2650, 1040, 0, 0, 0, 0]	
			},
			"otsu": {
				"rate": null,
				"amount": 30300
			}
		},
		{
			"boundary": 236000,
			"fuyou": {
				"rate": null,
				"amount": [5990, 4380, 2770, 1140, 0, 0, 0, 0]	
			},
			"otsu": {
				"rate": null,
				"amount": 31300
			}
		},
		{
			"boundary": 239000,
			"fuyou": {
				"rate": null,
				"amount": [6110, 4490, 2870, 1260, 0, 0, 0, 0]	
			},
			"otsu": {
				"rate": null,
				"amount": 32400
			}
		},
		{
			"boundary": 242000,
			"fuyou": {
				"rate": null,
				"amount": [6210, 4590, 2980, 1360, 0, 0, 0, 0]	
			},
			"otsu": {
				"rate": null,
				"amount": 33400
			}
		},
		{
			"boundary": 245000,
			"fuyou": {
				"rate": null,
				"amount": [6320, 4710, 3080, 1470, 0, 0, 0, 0]	
			},
			"otsu": {
				"rate": null,
				"amount": 34400
			}
		},
		{
			"boundary": 248000,
			"fuyou": {
				"rate": null,
				"amount": [6420, 4810, 3200, 1570, 0, 0, 0, 0]	
			},
			"otsu": {
				"rate": null,
				"amount": 35400
			}
		},
		{
			"boundary": 251000,
			"fuyou": {
				"rate": null,
				"amount": [6530, 4920, 3300, 1680, 0, 0, 0, 0]	
			},
			"otsu": {
				"rate": null,
				"amount": 36400
			}
		},
		{
			"boundary": 254000,
			"fuyou": {
				"rate": null,
				"amount": [6640, 5020, 3410, 1790, 170, 0, 0, 0]	
			},
			"otsu": {
				"rate": null,
				"amount": 37500
			}
		},
		{
			"boundary": 257000,
			"fuyou": {
				"rate": null,
				"amount": [6750, 5140, 3510, 1900, 290, 0, 0, 0]	
			},
			"otsu": {
				"rate": null,
				"amount": 38500
			}
		},
		{
			"boundary": 260000,
			"fuyou": {
				"rate": null,
				"amount": [6850, 5240, 3620, 2000, 390, 0, 0, 0]	
			},
			"otsu": {
				"rate": null,
				"amount": 39400
			}
		},
		{
			"boundary": 263000,
			"fuyou": {
				"rate": null,
				"amount": [6960, 5350, 3730, 2110, 500, 0, 0, 0]	
			},
			"otsu": {
				"rate": null,
				"amount": 40400
			}
		},
		{
			"boundary": 266000,
			"fuyou": {
				"rate": null,
				"amount": [7070, 5450, 3840, 2220, 600, 0, 0, 0]	
			},
			"otsu": {
				"rate": null,
				"amount": 41500
			}
		},
		{
			"boundary": 269000,
			"fuyou": {
				"rate": null,
				"amount": [7180, 5560, 3940, 2330, 710, 0, 0, 0]	
			},
			"otsu": {
				"rate": null,
				"amount": 42500
			}
		},
		{
			"boundary": 272000,
			"fuyou": {
				"rate": null,
				"amount": [7280, 5670, 4050, 2430, 820, 0, 0, 0]	
			},
			"otsu": {
				"rate": null,
				"amount": 43500
			}
		},
		{
			"boundary": 275000,
			"fuyou": {
				"rate": null,
				"amount": [7390, 5780, 4160, 2540, 930, 0, 0, 0]	
			},
			"otsu": {
				"rate": null,
				"amount": 44500
			}
		},
		{
			"boundary": 278000,
			"fuyou": {
				"rate": null,
				"amount": [7490, 5880, 4270, 2640, 1030, 0, 0, 0]	
			},
			"otsu": {
				"rate": null,
				"amount": 45500
			}
		},
		{
			"boundary": 281000,
			"fuyou": {
				"rate": null,
				"amount": [7610, 5990, 4370, 2760, 1140, 0, 0, 0]	
			},
			"otsu": {
				"rate": null,
				"amount": 46600
			}
		},
		{
			"boundary": 284000,
			"fuyou": {
				"rate": null,
				"amount": [7710, 6100, 4480, 2860, 1250, 0, 0, 0]	
			},
			"otsu": {
				"rate": null,
				"amount": 47600
			}
		},
		{
			"boundary": 287000,
			"fuyou": {
				"rate": null,
				"amount": [7820, 6210, 4580, 2970, 1360, 0, 0, 0]	
			},
			"otsu": {
				"rate": null,
				"amount": 48600
			}
		},
		{
			"boundary": 290000,
			"fuyou": {
				"rate": null,
				"amount": [7920, 6310, 4700, 3070, 1460, 0, 0, 0]	
			},
			"otsu": {
				"rate": null,
				"amount": 49700
			}
		},
		{
			"boundary": 293000,
			"fuyou": {
				"rate": null,
				"amount": [8040, 6420, 4800, 3190, 1570, 0, 0, 0]	
			},
			"otsu": {
				"rate": null,
				"amount": 50900
			}
		},
		{
			"boundary": 296000,
			"fuyou": {
				"rate": null,
				"amount": [8140, 6520, 4910, 3290, 1670, 0, 0, 0]	
			},
			"otsu": {
				"rate": null,
				"amount": 52100
			}
		},
		{
			"boundary": 299000,
			"fuyou": {
				"rate": null,
				"amount": [8250, 6640, 5010, 3400, 1790, 160, 0, 0]	
			},
			"otsu": {
				"rate": null,
				"amount": 52900
			}
		},
		{
			"boundary": 302000,
			"fuyou": {
				"rate": null,
				"amount": [8420, 6740, 5130, 3510, 1890, 280, 0, 0]	
			},
			"otsu": {
				"rate": null,
				"amount": 53700
			}
		},
		{
			"boundary": 305000,
			"fuyou": {
				"rate": null,
				"amount": [8670, 6860, 5250, 3630, 2010, 400, 0, 0]	
			},
			"otsu": {
				"rate": null,
				"amount": 54500
			}
		},
		{
			"boundary": 308000,
			"fuyou": {
				"rate": null,
				"amount": [8910, 6980, 5370, 3760, 2130, 520, 0, 0]	
			},
			"otsu": {
				"rate": null,
				"amount": 55200
			}
		},
		{
			"boundary": 311000,
			"fuyou": {
				"rate": null,
				"amount": [9160, 7110, 5490, 3880, 2260, 640, 0, 0]	
			},
			"otsu": {
				"rate": null,
				"amount": 56100
			}
		},
		{
			"boundary": 314000,
			"fuyou": {
				"rate": null,
				"amount": [9400, 7230, 5620, 4000, 2380, 770, 0, 0]	
			},
			"otsu": {
				"rate": null,
				"amount": 56900
			}
		},
		{
			"boundary": 317000,
			"fuyou": {
				"rate": null,
				"amount": [9650, 7350, 5740, 4120, 2500, 890, 0, 0]	
			},
			"otsu": {
				"rate": null,
				"amount": 57800
			}
		},
		{
			"boundary": 320000,
			"fuyou": {
				"rate": null,
				"amount": [9890, 7470, 5860, 4250, 2620, 1010, 0, 0]	
			},
			"otsu": {
				"rate": null,
				"amount": 58800
			}
		},
		{
			"boundary": 323000,
			"fuyou": {
				"rate": null,
				"amount": [10140, 7600, 5980, 4370, 2750, 1130, 0, 0]	
			},
			"otsu": {
				"rate": null,
				"amount": 59800
			}
		},
		{
			"boundary": 326000,
			"fuyou": {
				"rate": null,
				"amount": [10380, 7720, 6110, 4490, 2870, 1260, 0, 0]	
			},
			"otsu": {
				"rate": null,
				"amount": 60900
			}
		},
		{
			"boundary": 329000,
			"fuyou": {
				"rate": null,
				"amount": [10630, 7840, 6230, 4610, 2990, 1380, 0, 0]	
			},
			"otsu": {
				"rate": null,
				"amount": 61900
			}
		},
		{
			"boundary": 332000,
			"fuyou": {
				"rate": null,
				"amount": [10870, 7960, 6350, 4740, 3110, 1500, 0, 0]	
			},
			"otsu": {
				"rate": null,
				"amount": 62900
			}
		},
		{
			"boundary": 335000,
			"fuyou": {
				"rate": null,
				"amount": [11120, 8090, 6470, 4860, 3240, 1620, 0, 0]	
			},
			"otsu": {
				"rate": null,
				"amount": 63900
			}
		},
		{
			"boundary": 338000,
			"fuyou": {
				"rate": null,
				"amount": [11360, 8210, 6600, 4980, 3360, 1750, 130, 0]	
			},
			"otsu": {
				"rate": null,
				"amount": 64900
			}
		},
		{
			"boundary": 341000,
			"fuyou": {
				"rate": null,
				"amount": [11610, 8370, 6720, 5110, 3480, 1870, 260, 0]	
			},
			"otsu": {
				"rate": null,
				"amount": 66000
			}
		},
		{
			"boundary": 344000,
			"fuyou": {
				"rate": null,
				"amount": [11850, 8620, 6840, 5230, 3600, 1990, 380, 0]	
			},
			"otsu": {
				"rate": null,
				"amount": 67000
			}
		},
		{
			"boundary": 347000,
			"fuyou": {
				"rate": null,
				"amount": [12100, 8860, 6960, 5350, 3730, 2110, 500, 0]	
			},
			"otsu": {
				"rate": null,
				"amount": 68000
			}
		},
		{
			"boundary": 350000,
			"fuyou": {
				"rate": null,
				"amount": [12340, 9110, 7090, 5470, 3850, 2240, 620, 0]	
			},
			"otsu": {
				"rate": null,
				"amount": 69000
			}
		},
		{
			"boundary": 353000,
			"fuyou": {
				"rate": null,
				"amount": [12590, 9350, 7210, 5600, 3970, 2360, 750, 0]	
			},
			"otsu": {
				"rate": null,
				"amount": 70000
			}
		},
		{
			"boundary": 356000,
			"fuyou": {
				"rate": null,
				"amount": [12830, 9600, 7330, 5720, 4090, 2480, 870, 0]	
			},
			"otsu": {
				"rate": null,
				"amount": 71100
			}
		},
		{
			"boundary": 359000,
			"fuyou": {
				"rate": null,
				"amount": [13080, 9840, 7450, 5840, 4220, 2600, 990, 0]	
			},
			"otsu": {
				"rate": null,
				"amount": 72100
			}
		},
		{
			"boundary": 362000,
			"fuyou": {
				"rate": null,
				"amount": [13320, 10090, 7580, 5960, 4340, 2730, 1110, 0]	
			},
			"otsu": {
				"rate": null,
				"amount": 73100
			}
		},
		{
			"boundary": 365000,
			"fuyou": {
				"rate": null,
				"amount": [13570, 10330, 7700, 6090, 4460, 2850, 1240, 0]	
			},
			"otsu": {
				"rate": null,
				"amount": 74200
			}
		},
		{
			"boundary": 368000,
			"fuyou": {
				"rate": null,
				"amount": [13810, 10580, 7820, 6210, 4580, 2970, 1360, 0]	
			},
			"otsu": {
				"rate": null,
				"amount": 75200
			}
		},
		{
			"boundary": 371000,
			"fuyou": {
				"rate": null,
				"amount": [14060, 10820, 7940, 6330, 4710, 3090, 1480, 0]	
			},
			"otsu": {
				"rate": null,
				"amount": 76200
			}
		},
		{
			"boundary": 374000,
			"fuyou": {
				"rate": null,
				"amount": [14300, 11070, 8070, 6450, 4830, 3220, 1600, 0]	
			},
			"otsu": {
				"rate": null,
				"amount": 77100
			}
		},
		{
			"boundary": 377000,
			"fuyou": {
				"rate": null,
				"amount": [14550, 11310, 8190, 6580, 4950, 3340, 1730, 100]	
			},
			"otsu": {
				"rate": null,
				"amount": 78100
			}
		},
		{
			"boundary": 380000,
			"fuyou": {
				"rate": null,
				"amount": [14790, 11560, 8320, 6700, 5070, 3460, 1850, 220]	
			},
			"otsu": {
				"rate": null,
				"amount": 79000
			}
		},
		{
			"boundary": 383000,
			"fuyou": {
				"rate": null,
				"amount": [15040, 11800, 8570, 6820, 5200, 3580, 1970, 350]	
			},
			"otsu": {
				"rate": null,
				"amount": 79900
			}
		},
		{
			"boundary": 386000,
			"fuyou": {
				"rate": null,
				"amount": [15280, 12050, 8810, 6940, 5320, 3710, 2090, 470]	
			},
			"otsu": {
				"rate": null,
				"amount": 81400
			}
		},
		{
			"boundary": 389000,
			"fuyou": {
				"rate": null,
				"amount": [15530, 12290, 9060, 7070, 5440, 3830, 2220, 590]	
			},
			"otsu": {
				"rate": null,
				"amount": 83100
			}
		},
		{
			"boundary": 392000,
			"fuyou": {
				"rate": null,
				"amount": [15770, 12540, 9300, 7190, 5560, 3950, 2340, 710]	
			},
			"otsu": {
				"rate": null,
				"amount": 84700
			}
		},
		{
			"boundary": 395000,
			"fuyou": {
				"rate": null,
				"amount": [16020, 12780, 9550, 7310, 5690, 4070, 2460, 840]	
			},
			"otsu": {
				"rate": null,
				"amount": 86500
			}
		},
		{
			"boundary": 398000,
			"fuyou": {
				"rate": null,
				"amount": [16260, 13030, 9790, 7430, 5810, 4200, 2580, 960]	
			},
			"otsu": {
				"rate": null,
				"amount": 88200
			}
		},
		{
			"boundary": 401000,
			"fuyou": {
				"rate": null,
				"amount": [16510, 13270, 10040, 7560, 5930, 4320, 2710, 1080]	
			},
			"otsu": {
				"rate": null,
				"amount": 89800
			}
		},
		{
			"boundary": 404000,
			"fuyou": {
				"rate": null,
				"amount": [16750, 13520, 10280, 7680, 6050, 4440, 2830, 1200]	
			},
			"otsu": {
				"rate": null,
				"amount": 91600
			}
		},
		{
			"boundary": 407000,
			"fuyou": {
				"rate": null,
				"amount": [17000, 13760, 10530, 7800, 6180, 4560, 2950, 1330]	
			},
			"otsu": {
				"rate": null,
				"amount": 93300
			}
		},
		{
			"boundary": 410000,
			"fuyou": {
				"rate": null,
				"amount": [17240, 14010, 10770, 7920, 6300, 4690, 3070, 1450]	
			},
			"otsu": {
				"rate": null,
				"amount": 95000
			}
		},
		{
			"boundary": 413000,
			"fuyou": {
				"rate": null,
				"amount": [17490, 14250, 11020, 8050, 6420, 4810, 3200, 1570]	
			},
			"otsu": {
				"rate": null,
				"amount": 96700
			}
		},
		{
			"boundary": 416000,
			"fuyou": {
				"rate": null,
				"amount": [17730, 14500, 11260, 8170, 6540, 4930, 3320, 1690]	
			},
			"otsu": {
				"rate": null,
				"amount": 98300
			}
		},
		{
			"boundary": 419000,
			"fuyou": {
				"rate": null,
				"amount": [17980, 14740, 11510, 8290, 6670, 5050, 3440, 1820]	
			},
			"otsu": {
				"rate": null,
				"amount": 100100
			}
		},
		{
			"boundary": 422000,
			"fuyou": {
				"rate": null,
				"amount": [18220, 14990, 11750, 8530, 6790, 5180, 3560, 1940]	
			},
			"otsu": {
				"rate": null,
				"amount": 101800
			}
		},
		{
			"boundary": 425000,
			"fuyou": {
				"rate": null,
				"amount": [18470, 15230, 12000, 8770, 6910, 5300, 3690, 2060]	
			},
			"otsu": {
				"rate": null,
				"amount": 103400
			}
		},
		{
			"boundary": 428000,
			"fuyou": {
				"rate": null,
				"amount": [18710, 15480, 12240, 9020, 7030, 5420, 3810, 2180]	
			},
			"otsu": {
				"rate": null,
				"amount": 105200
			}
		},
		{
			"boundary": 431000,
			"fuyou": {
				"rate": null,
				"amount": [18960, 15720, 12490, 9260, 7160, 5540, 3930, 2310]	
			},
			"otsu": {
				"rate": null,
				"amount": 106900
			}
		},
		{
			"boundary": 434000,
			"fuyou": {
				"rate": null,
				"amount": [19210, 15970, 12730, 9510, 7280, 5670, 4050, 2430]	
			},
			"otsu": {
				"rate": null,
				"amount": 108500
			}
		},
		{
			"boundary": 437000,
			"fuyou": {
				"rate": null,
				"amount": [19450, 16210, 12980, 9750, 7400, 5790, 4180, 2550]	
			},
			"otsu": {
				"rate": null,
				"amount": 110300
			}
		},
		{
			"boundary": 440000,
			"fuyou": {
				"rate": null,
				"amount": [19700, 16460, 13220, 10000, 7520, 5910, 4300, 2680]	
			},
			"otsu": {
				"rate": null,
				"amount": 112000
			}
		},
		{
			"boundary": 443000,
			"fuyou": {
				"rate": null,
				"amount": [20090, 16700, 13470, 10240, 7650, 6030, 4420, 2800]	
			},
			"otsu": {
				"rate": null,
				"amount": 113600
			}
		},
		{
			"boundary": 446000,
			"fuyou": {
				"rate": null,
				"amount": [20580, 16950, 13710, 10490, 7770, 6160, 4540, 2920]	
			},
			"otsu": {
				"rate": null,
				"amount": 115400
			}
		},
		{
			"boundary": 449000,
			"fuyou": {
				"rate": null,
				"amount": [21070, 17190, 13960, 10730, 7890, 6280, 4670, 3040]	
			},
			"otsu": {
				"rate": null,
				"amount": 117100
			}
		},
		{
			"boundary": 452000,
			"fuyou": {
				"rate": null,
				"amount": [21560, 17440, 14200, 10980, 8010, 6400, 4790, 3170]	
			},
			"otsu": {
				"rate": null,
				"amount": 118700
			}
		},
		{
			"boundary": 455000,
			"fuyou": {
				"rate": null,
				"amount": [22050, 17680, 14450, 11220, 8140, 6520, 4910, 3290]	
			},
			"otsu": {
				"rate": null,
				"amount": 120500
			}
		},
		{
			"boundary": 458000,
			"fuyou": {
				"rate": null,
				"amount": [22540, 17930, 14690, 11470, 8260, 6650, 5030, 3410]	
			},
			"otsu": {
				"rate": null,
				"amount": 122200
			}
		},
		{
			"boundary": 461000,
			"fuyou": {
				"rate": null,
				"amount": [23030, 18170, 14940, 11710, 8470, 6770, 5160, 3530]	
			},
			"otsu": {
				"rate": null,
				"amount": 123800
			}
		},
		{
			"boundary": 464000,
			"fuyou": {
				"rate": null,
				"amount": [23520, 18420, 15180, 11960, 8720, 6890, 5280, 3660]	
			},
			"otsu": {
				"rate": null,
				"amount": 125600
			}
		},
		{
			"boundary": 467000,
			"fuyou": {
				"rate": null,
				"amount": [24010, 18660, 15430, 12200, 8960, 7010, 5400, 3780]	
			},
			"otsu": {
				"rate": null,
				"amount": 127300
			}
		},
		{
			"boundary": 470000,
			"fuyou": {
				"rate": null,
				"amount": [24500, 18910, 15670, 12450, 9210, 7140, 5520, 3900]	
			},
			"otsu": {
				"rate": null,
				"amount": 129000
			}
		},
		{
			"boundary": 473000,
			"fuyou": {
				"rate": null,
				"amount": [24990, 19150, 15920, 12690, 9450, 7260, 5650, 4020]	
			},
			"otsu": {
				"rate": null,
				"amount": 130700
			}
		},
		{
			"boundary": 476000,
			"fuyou": {
				"rate": null,
				"amount": [25480, 19400, 16160, 12940, 9700, 7380, 5770, 4150]	
			},
			"otsu": {
				"rate": null,
				"amount": 132300
			}
		},
		{
			"boundary": 479000,
			"fuyou": {
				"rate": null,
				"amount": [25970, 19640, 16410, 13180, 9940, 7500, 5890, 4270]	
			},
			"otsu": {
				"rate": null,
				"amount": 134000
			}
		},
		{
			"boundary": 482000,
			"fuyou": {
				"rate": null,
				"amount": [26460, 20000, 16650, 13430, 10190, 7630, 6010, 4390]	
			},
			"otsu": {
				"rate": null,
				"amount": 135600
			}
		},
		{
			"boundary": 485000,
			"fuyou": {
				"rate": null,
				"amount": [26950, 20490, 16900, 13670, 10430, 7750, 6140, 4510]	
			},
			"otsu": {
				"rate": null,
				"amount": 137200
			}
		},
		{
			"boundary": 488000,
			"fuyou": {
				"rate": null,
				"amount": [27440, 20980, 17140, 13920, 10680, 7870, 6260, 4640]	
			},
			"otsu": {
				"rate": null,
				"amount": 138800
			}
		},
		{
			"boundary": 491000,
			"fuyou": {
				"rate": null,
				"amount": [27930, 21470, 17390, 14160, 10920, 7990, 6380, 4760]	
			},
			"otsu": {
				"rate": null,
				"amount": 140400
			}
		},
		{
			"boundary": 494000,
			"fuyou": {
				"rate": null,
				"amount": [28420, 21960, 17630, 14410, 11170, 8120, 6500, 4880]	
			},
			"otsu": {
				"rate": null,
				"amount": 142000
			}
		},
		{
			"boundary": 497000,
			"fuyou": {
				"rate": null,
				"amount": [28910, 22450, 17880, 14650, 11410, 8240, 6630, 5000]	
			},
			"otsu": {
				"rate": null,
				"amount": 143700
			}
		},
		{
			"boundary": 500000,
			"fuyou": {
				"rate": null,
				"amount": [29400, 22940, 18120, 14900, 11660, 8420, 6750, 5130]	
			},
			"otsu": {
				"rate": null,
				"amount": 145200
			}
		},
		{
			"boundary": 503000,
			"fuyou": {
				"rate": null,
				"amount": [29890, 23430, 18370, 15140, 11900, 8670, 6870, 5250]	
			},
			"otsu": {
				"rate": null,
				"amount": 146800
			}
		},
		{
			"boundary": 506000,
			"fuyou": {
				"rate": null,
				"amount": [30380, 23920, 18610, 15390, 12150, 8910, 6990, 5370]	
			},
			"otsu": {
				"rate": null,
				"amount": 148500
			}
		},
		{
			"boundary": 509000,
			"fuyou": {
				"rate": null,
				"amount": [30880, 24410, 18860, 15630, 12390, 9160, 7120, 5490]	
			},
			"otsu": {
				"rate": null,
				"amount": 150100
			}
		},
		{
			"boundary": 512000,
			"fuyou": {
				"rate": null,
				"amount": [31370, 24900, 19100, 15880, 12640, 9400, 7240, 5620]	
			},
			"otsu": {
				"rate": null,
				"amount": 151600
			}
		},
		{
			"boundary": 515000,
			"fuyou": {
				"rate": null,
				"amount": [31860, 25390, 19350, 16120, 12890, 9650, 7360, 5740]	
			},
			"otsu": {
				"rate": null,
				"amount": 153300
			}
		},
		{
			"boundary": 518000,
			"fuyou": {
				"rate": null,
				"amount": [32350, 25880, 19590, 16370, 13130, 9890, 7480, 5860]	
			},
			"otsu": {
				"rate": null,
				"amount": 154900
			}
		},
		{
			"boundary": 521000,
			"fuyou": {
				"rate": null,
				"amount": [32840, 26370, 19900, 16610, 13380, 10140, 7610, 5980]	
			},
			"otsu": {
				"rate": null,
				"amount": 156500
			}
		},
		{
			"boundary": 524000,
			"fuyou": {
				"rate": null,
				"amount": [33330, 26860, 20390, 16860, 13620, 10380, 7730, 6110]	
			},
			"otsu": {
				"rate": null,
				"amount": 158100
			}
		},
		{
			"boundary": 527000,
			"fuyou": {
				"rate": null,
				"amount": [33820, 27350, 20880, 17100, 13870, 10630, 7850, 6230]	
			},
			"otsu": {
				"rate": null,
				"amount": 159600
			}
		},
		{
			"boundary": 530000,
			"fuyou": {
				"rate": null,
				"amount": [34310, 27840, 21370, 17350, 14110, 10870, 7970, 6350]	
			},
			"otsu": {
				"rate": null,
				"amount": 161000
			}
		},
		{
			"boundary": 533000,
			"fuyou": {
				"rate": null,
				"amount": [34800, 28330, 21860, 17590, 14360, 11120, 8100, 6470]	
			},
			"otsu": {
				"rate": null,
				"amount": 162500
			}
		},
		{
			"boundary": 536000,
			"fuyou": {
				"rate": null,
				"amount": [35290, 28820, 22350, 17840, 14600, 11360, 8220, 6600]	
			},
			"otsu": {
				"rate": null,
				"amount": 164000
			}
		},
		{
			"boundary": 539000,
			"fuyou": {
				"rate": null,
				"amount": [35780, 29310, 22840, 18080, 14850, 11610, 8380, 6720]	
			},
			"otsu": {
				"rate": null,
				"amount": 165400
			}
		},
		{
			"boundary": 542000,
			"fuyou": {
				"rate": null,
				"amount": [36270, 29800, 23330, 18330, 15090, 11850, 8630, 6840]	
			},
			"otsu": {
				"rate": null,
				"amount": 166900
			}
		},
		{
			"boundary": 545000,
			"fuyou": {
				"rate": null,
				"amount": [36760, 30290, 23820, 18570, 15340, 12100, 8870, 6960]	
			},
			"otsu": {
				"rate": null,
				"amount": 168400
			}
		},
		{
			"boundary": 548000,
			"fuyou": {
				"rate": null,
				"amount": [37250, 30780, 24310, 18820, 15580, 12340, 9120, 7090]	
			},
			"otsu": {
				"rate": null,
				"amount": 169900
			}
		},
		{
			"boundary": 551000,
			"fuyou": {
				"rate": null,
				"amount": [37740, 31270, 24800, 19060, 15830, 12590, 9360, 7210]	
			},
			"otsu": {
				"rate": null,
				"amount": 171300
			}
		},
		{
			"boundary": 554000,
			"fuyou": {
				"rate": null,
				"amount": [38280, 31810, 25340, 19330, 16100, 12860, 9630, 7350]	
			},
			"otsu": {
				"rate": null,
				"amount": 172800
			}
		},
		{
			"boundary": 557000,
			"fuyou": {
				"rate": null,
				"amount": [38830, 32370, 25890, 19600, 16380, 13140, 9900, 7480]	
			},
			"otsu": {
				"rate": null,
				"amount": 174300
			}
		},
		{
			"boundary": 560000,
			"fuyou": {
				"rate": null,
				"amount": [39380, 32920, 26440, 19980, 16650, 13420, 10180, 7630]	
			},
			"otsu": {
				"rate": null,
				"amount": 175700
			}
		},
		{
			"boundary": 563000,
			"fuyou": {
				"rate": null,
				"amount": [39930, 33470, 27000, 20530, 16930, 13690, 10460, 7760]	
			},
			"otsu": {
				"rate": null,
				"amount": 177200
			}
		},
		{
			"boundary": 566000,
			"fuyou": {
				"rate": null,
				"amount": [40480, 34020, 27550, 21080, 17200, 13970, 10730, 7900]	
			},
			"otsu": {
				"rate": null,
				"amount": 178700
			}
		},
		{
			"boundary": 569000,
			"fuyou": {
				"rate": null,
				"amount": [41030, 34570, 28100, 21630, 17480, 14240, 11010, 8040]	
			},
			"otsu": {
				"rate": null,
				"amount": 180100
			}
		},
		{
			"boundary": 572000,
			"fuyou": {
				"rate": null,
				"amount": [41590, 35120, 28650, 22190, 17760, 14520, 11280, 8180]	
			},
			"otsu": {
				"rate": null,
				"amount": 181600
			}
		},
		{
			"boundary": 575000,
			"fuyou": {
				"rate": null,
				"amount": [42140, 35670, 29200, 22740, 18030, 14790, 11560, 8330]	
			},
			"otsu": {
				"rate": null,
				"amount": 183100
			}
		},
		{
			"boundary": 578000,
			"fuyou": {
				"rate": null,
				"amount": [42690, 36230, 29750, 23290, 18310, 15070, 11830, 8610]	
			},
			"otsu": {
				"rate": null,
				"amount": 184600
			}
		},
		{
			"boundary": 581000,
			"fuyou": {
				"rate": null,
				"amount": [43240, 36780, 30300, 23840, 18580, 15350, 12110, 8880]	
			},
			"otsu": {
				"rate": null,
				"amount": 186000
			}
		},
		{
			"boundary": 584000,
			"fuyou": {
				"rate": null,
				"amount": [43790, 37330, 30850, 24390, 18860, 15620, 12380, 9160]	
			},
			"otsu": {
				"rate": null,
				"amount": 187500
			}
		},
		{
			"boundary": 587000,
			"fuyou": {
				"rate": null,
				"amount": [44340, 37880, 31410, 24940, 19130, 15900, 12660, 9430]	
			},
			"otsu": {
				"rate": null,
				"amount": 189000
			}
		},
		{
			"boundary": 590000,
			"fuyou": {
				"rate": null,
				"amount": [44890, 38430, 31960, 25490, 19410, 16170, 12940, 9710]	
			},
			"otsu": {
				"rate": null,
				"amount": 190400
			}
		},
		{
			"boundary": 593000,
			"fuyou": {
				"rate": null,
				"amount": [45440, 38980, 32510, 26050, 19680, 16450, 13210, 9990]	
			},
			"otsu": {
				"rate": null,
				"amount": 191900
			}
		},
		{
			"boundary": 596000,
			"fuyou": {
				"rate": null,
				"amount": [46000, 39530, 33060, 26600, 20130, 16720, 13490, 10260]	
			},
			"otsu": {
				"rate": null,
				"amount": 193400
			}
		},
		{
			"boundary": 599000,
			"fuyou": {
				"rate": null,
				"amount": [46550, 40080, 33610, 27150, 20690, 17000, 13760, 10540]	
			},
			"otsu": {
				"rate": null,
				"amount": 194800
			}
		},
		{
			"boundary": 602000,
			"fuyou": {
				"rate": null,
				"amount": [47100, 40640, 34160, 27700, 21240, 17280, 14040, 10810]	
			},
			"otsu": {
				"rate": null,
				"amount": 196300
			}
		},
		{
			"boundary": 605000,
			"fuyou": {
				"rate": null,
				"amount": [47650, 41190, 34710, 28250, 21790, 17550, 14310, 11090]	
			},
			"otsu": {
				"rate": null,
				"amount": 197800
			}
		},
		{
			"boundary": 608000,
			"fuyou": {
				"rate": null,
				"amount": [48200, 41740, 35270, 28800, 22340, 17830, 14590, 11360]	
			},
			"otsu": {
				"rate": null,
				"amount": 199300
			}
		},
		{
			"boundary": 611000,
			"fuyou": {
				"rate": null,
				"amount": [48750, 42290, 35820, 29350, 22890, 18100, 14870, 11640]	
			},
			"otsu": {
				"rate": null,
				"amount": 200700
			}
		},
		{
			"boundary": 614000,
			"fuyou": {
				"rate": null,
				"amount": [49300, 42840, 36370, 29910, 23440, 18380, 15140, 11920]	
			},
			"otsu": {
				"rate": null,
				"amount": 202200
			}
		},
		{
			"boundary": 617000,
			"fuyou": {
				"rate": null,
				"amount": [49860, 43390, 36920, 30460, 23990, 18650, 15420, 12190]	
			},
			"otsu": {
				"rate": null,
				"amount": 203700
			}
		},
		{
			"boundary": 620000,
			"fuyou": {
				"rate": null,
				"amount": [50410, 43940, 37470, 31010, 24540, 18930, 15690, 12470]	
			},
			"otsu": {
				"rate": null,
				"amount": 205100
			}
		},
		{
			"boundary": 623000,
			"fuyou": {
				"rate": null,
				"amount": [50960, 44500, 38020, 31560, 25100, 19210, 15970, 12740]	
			},
			"otsu": {
				"rate": null,
				"amount": 206700
			}
		},
		{
			"boundary": 626000,
			"fuyou": {
				"rate": null,
				"amount": [51510, 45050, 38570, 32110, 25650, 19480, 16240, 13020]	
			},
			"otsu": {
				"rate": null,
				"amount": 208100
			}
		},
		{
			"boundary": 629000,
			"fuyou": {
				"rate": null,
				"amount": [52060, 45600, 39120, 32660, 26200, 19760, 16520, 13290]	
			},
			"otsu": {
				"rate": null,
				"amount": 209500
			}
		},
		{
			"boundary": 632000,
			"fuyou": {
				"rate": null,
				"amount": [52610, 46150, 39680, 33210, 26750, 20280, 16800, 13570]	
			},
			"otsu": {
				"rate": null,
				"amount": 211000
			}
		},
		{
			"boundary": 635000,
			"fuyou": {
				"rate": null,
				"amount": [53160, 46700, 40230, 33760, 27300, 20830, 17070, 13840]	
			},
			"otsu": {
				"rate": null,
				"amount": 212500
			}
		},
		{
			"boundary": 638000,
			"fuyou": {
				"rate": null,
				"amount": [53710, 47250, 40780, 34320, 27850, 21380, 17350, 14120]	
			},
			"otsu": {
				"rate": null,
				"amount": 214000
			}
		},
		{
			"boundary": 641000,
			"fuyou": {
				"rate": null,
				"amount": [54270, 47800, 41330, 34870, 28400, 21930, 17620, 14400]	
			},
			"otsu": {
				"rate": null,
				"amount": 214900
			}
		},
		{
			"boundary": 644000,
			"fuyou": {
				"rate": null,
				"amount": [54820, 48350, 41880, 35420, 28960, 22480, 17900, 14670]	
			},
			"otsu": {
				"rate": null,
				"amount": 215900
			}
		},
		{
			"boundary": 647000,
			"fuyou": {
				"rate": null,
				"amount": [55370, 48910, 42430, 35970, 29510, 23030, 18170, 14950]	
			},
			"otsu": {
				"rate": null,
				"amount": 217000
			}
		},
		{
			"boundary": 650000,
			"fuyou": {
				"rate": null,
				"amount": [55920, 49460, 42980, 36520, 30060, 23590, 18450, 15220]	
			},
			"otsu": {
				"rate": null,
				"amount": 218000
			}
		},
		{
			"boundary": 653000,
			"fuyou": {
				"rate": null,
				"amount": [56470, 50010, 43540, 37070, 30610, 24140, 18730, 15500]	
			},
			"otsu": {
				"rate": null,
				"amount": 219000
			}
		},
		{
			"boundary": 656000,
			"fuyou": {
				"rate": null,
				"amount": [57020, 50560, 44090, 37620, 31160, 24690, 19000, 15770]	
			},
			"otsu": {
				"rate": null,
				"amount": 220000
			}
		},
		{
			"boundary": 659000,
			"fuyou": {
				"rate": null,
				"amount": [57570, 51110, 44640, 38180, 31710, 25240, 19280, 16050]	
			},
			"otsu": {
				"rate": null,
				"amount": 221000
			}
		},
		{
			"boundary": 662000,
			"fuyou": {
				"rate": null,
				"amount": [58130, 51660, 45190, 38730, 32260, 25790, 19550, 16330]	
			},
			"otsu": {
				"rate": null,
				"amount": 222100
			}
		},
		{
			"boundary": 665000,
			"fuyou": {
				"rate": null,
				"amount": [58680, 52210, 45740, 39280, 32810, 26340, 19880, 16600]	
			},
			"otsu": {
				"rate": null,
				"amount": 223100
			}
		},
		{
			"boundary": 668000,
			"fuyou": {
				"rate": null,
				"amount": [59230, 52770, 46290, 39830, 33370, 26890, 20430, 16880]	
			},
			"otsu": {
				"rate": null,
				"amount": 224100
			}
		},
		{
			"boundary": 671000,
			"fuyou": {
				"rate": null,
				"amount": [59780, 53320, 46840, 40380, 33920, 27440, 20980, 17150]	
			},
			"otsu": {
				"rate": null,
				"amount": 225000
			}
		},
		{
			"boundary": 674000,
			"fuyou": {
				"rate": null,
				"amount": [60330, 53870, 47390, 40930, 34470, 28000, 21530, 17430]	
			},
			"otsu": {
				"rate": null,
				"amount": 226000
			}
		},
		{
			"boundary": 677000,
			"fuyou": {
				"rate": null,
				"amount": [60880, 54420, 47950, 41480, 35020, 28550, 22080, 17700]	
			},
			"otsu": {
				"rate": null,
				"amount": 227100
			}
		},
		{
			"boundary": 680000,
			"fuyou": {
				"rate": null,
				"amount": [61430, 54970, 48500, 42030, 35570, 29100, 22640, 17980]	
			},
			"otsu": {
				"rate": null,
				"amount": 228100
			}
		},
		{
			"boundary": 683000,
			"fuyou": {
				"rate": null,
				"amount": [61980, 55520, 49050, 42590, 36120, 29650, 23190, 18260]	
			},
			"otsu": {
				"rate": null,
				"amount": 229100
			}
		},
		{
			"boundary": 686000,
			"fuyou": {
				"rate": null,
				"amount": [62540, 56070, 49600, 43140, 36670, 30200, 23740, 18530]	
			},
			"otsu": {
				"rate": null,
				"amount": 230400
			}
		},
		{
			"boundary": 689000,
			"fuyou": {
				"rate": null,
				"amount": [63090, 56620, 50150, 43690, 37230, 30750, 24290, 18810]	
			},
			"otsu": {
				"rate": null,
				"amount": 232100
			}
		},
		{
			"boundary": 692000,
			"fuyou": {
				"rate": null,
				"amount": [63640, 57180, 50700, 44240, 37780, 31300, 24840, 19080]	
			},
			"otsu": {
				"rate": null,
				"amount": 233600
			}
		},
		{
			"boundary": 695000,
			"fuyou": {
				"rate": null,
				"amount": [64190, 57730, 51250, 44790, 38330, 31860, 25390, 19360]	
			},
			"otsu": {
				"rate": null,
				"amount": 235100
			}
		},
		{
			"boundary": 698000,
			"fuyou": {
				"rate": null,
				"amount": [64740, 58280, 51810, 45340, 38880, 32410, 25940, 19630]	
			},
			"otsu": {
				"rate": null,
				"amount": 236700
			}
		},
		{
			"boundary": 701000,
			"fuyou": {
				"rate": null,
				"amount": [65290, 58830, 52360, 45890, 39430, 32960, 26490, 20030]	
			},
			"otsu": {
				"rate": null,
				"amount": 238200
			}
		},
		{
			"boundary": 704000,
			"fuyou": {
				"rate": null,
				"amount": [65840, 59380, 52910, 46450, 39980, 33510, 27050, 20580]	
			},
			"otsu": {
				"rate": null,
				"amount": 239700
			}
		},
		{
			"boundary": 707000,
			"fuyou": {
				"rate": null,
				"amount": [66400, 59930, 53460, 47000, 40530, 34060, 27600, 21130]	
			},
			"otsu": {
				"rate": null,
				"amount": 241300
			}
		},
		{
			"boundary": 710000,
			"fuyou": {
				"rate": null,
				"amount": [66960, 60480, 54020, 47550, 41090, 34620, 28150, 21690]	
			},
			"otsu": {
				"rate": null,
				"amount": 242900
			}
		},
		{
			"boundary": 713000,
			"fuyou": {
				"rate": null,
				"amount": [67570, 61100, 54630, 48160, 41700, 35230, 28760, 22300]	
			},
			"otsu": {
				"rate": null,
				"amount": 244400
			}
		},
		{
			"boundary": 716000,
			"fuyou": {
				"rate": null,
				"amount": [68180, 61710, 55250, 48770, 42310, 35850, 29370, 22910]	
			},
			"otsu": {
				"rate": null,
				"amount": 246000
			}
		},
		{
			"boundary": 719000,
			"fuyou": {
				"rate": null,
				"amount": [68790, 62320, 55860, 49390, 42920, 36460, 29990, 23520]	
			},
			"otsu": {
				"rate": null,
				"amount": 247500
			}
		},
		{
			"boundary": 722000,
			"fuyou": {
				"rate": null,
				"amount": [69410, 62930, 56470, 50000, 43540, 37070, 30600, 24140]	
			},
			"otsu": {
				"rate": null,
				"amount": 249000
			}
		},
		{
			"boundary": 725000,
			"fuyou": {
				"rate": null,
				"amount": [70020, 63550, 57080, 50610, 44150, 37690, 31210, 24750]	
			},
			"otsu": {
				"rate": null,
				"amount": 250600
			}
		},
		{
			"boundary": 728000,
			"fuyou": {
				"rate": null,
				"amount": [70630, 64160, 57700, 51220, 44760, 38300, 31820, 25360]	
			},
			"otsu": {
				"rate": null,
				"amount": 252200
			}
		},
		{
			"boundary": 731000,
			"fuyou": {
				"rate": null,
				"amount": [71250, 64770, 58310, 51840, 45370, 38910, 32440, 25970]	
			},
			"otsu": {
				"rate": null,
				"amount": 253700
			}
		},
		{
			"boundary": 734000,
			"fuyou": {
				"rate": null,
				"amount": [71860, 65380, 58920, 52450, 45990, 39520, 33050, 26590]	
			},
			"otsu": {
				"rate": null,
				"amount": 255300
			}
		},
		{
			"boundary": 737000,
			"fuyou": {
				"rate": null,
				"amount": [72470, 66000, 59530, 53060, 46600, 40140, 33660, 27200]	
			},
			"otsu": {
				"rate": null,
				"amount": 256800
			}
		},
		{
			"boundary": 740000,
			"fuyou": {
				"rate": null,
				"amount": [73080, 66610, 60150, 53670, 47210, 40750, 34270, 27810]	
			},
			"otsu": {
				"rate": null,
				"amount": 258300
			}
		},
		{
			"boundary": 780000,
			"fuyou": {
				"rate": 20.42,
				"amount": [73390, 66920, 60450, 53980, 47520, 41050, 34580, 28120]	
			},
			"otsu": {
				"rate": 40.84,
				"amount": 259800
			}
		},
		{
			"boundary": 950000,
			"fuyou": {
				"rate": 23.483,
				"amount": [81560, 75090, 68620, 62150, 55690, 49220, 42750, 36290]	
			},
			"otsu": {
				"rate": 40.84,
				"amount": 259800
			}
		},
		{
			"boundary": 1700000,
			"fuyou": {
				"rate": 33.693,
				"amount": [121480, 115010, 108540, 102070, 95610, 89140, 82670, 76210]	
			},
			"otsu": {
				"rate": 45.945,
				"amount": 259800
			}
		},
		{
			"boundary": 2170000,
			"fuyou": {
				"rate": 40.84,
				"amount": [374180, 367710, 361240, 354770, 348310, 341840, 335370, 328910]	
			},
			"otsu": {
				"rate": 45.945,
				"amount": 651900
			}
		},
		{
			"boundary": 2210000,
			"fuyou": {
				"rate": 40.84,
				"amount": [571570, 565090, 558630, 552160, 545690, 539230, 532760, 526290]	
			},
			"otsu": {
				"rate": 45.945,
				"amount": 651900
			}
		},
		{
			"boundary": 2250000,
			"fuyou": {
				"rate": 40.84,
				"amount": [593340, 586870, 580410, 573930, 567470, 561010, 554540, 548070]	
			},
			"otsu": {
				"rate": 45.945,
				"amount": 651900
			}
		},
		{
			"boundary": 3500000,
			"fuyou": {
				"rate": 40.84,
				"amount": [615120, 608650, 602190, 595710, 589250, 582790, 576310, 569850]	
			},
			"otsu": {
				"rate": 45.945,
				"amount": 651900
			}
		},
		{
			"boundary": null,
			"fuyou": {
				"rate": 45.945,
				"amount": [1125620, 1119150, 1112690, 1106210, 1099750, 1093290, 1086810, 1080350]	
			},
			"otsu": {
				"rate": 45.945,
				"amount": 651900
			}
		}
	]
}
